pysdbots/__init__.py
pysdbots/__version__.py
pysdbots/pysdbots.py
pysdbots-3.2.dist-info/LICENSE
pysdbots-3.2.dist-info/METADATA
pysdbots-3.2.dist-info/WHEEL
pysdbots-3.2.dist-info/top_level.txt
pysdbots-3.2.dist-info/RECORD
