Metadata-Version: 2.1
Name: pysdbots
Version: 3.2
Summary: A Project Made To Centralize Various APIs 📖 No Authorization Needed :)
Home-page: https://github.com/Damantha126/pysdbots
Author: DamanthaJasinghe
Author-email: damanthaja@gmail.com
License: MIT
Project-URL: Tracker, https://github.com/Damantha126/pysdbots/issues
Project-URL: Community, https://t.me/SDBOTs_inifinity
Project-URL: Source, https://github.com/Damantha126/pysdbots
Project-URL: Documentation, https://docs.sdbots.tech
Keywords: sdbots,python-pakage,sd-api,api,damanthaja,mritzme,damantha126,pysdbots,jasinghe,damantha-jasinghe
Classifier: Development Status :: 5 - Production/Stable
Classifier: Intended Audience :: Developers
Classifier: License :: OSI Approved :: MIT License
Classifier: Programming Language :: Python
Classifier: Programming Language :: Python :: 3
Classifier: Programming Language :: Python :: 3.7
Classifier: Programming Language :: Python :: 3.8
Classifier: Programming Language :: Python :: 3.9
Classifier: Programming Language :: Python :: 3.10
Classifier: Programming Language :: Python :: 3.11
Classifier: Programming Language :: Python :: 3.12
License-File: LICENSE
Requires-Dist: requests >=2.28.1
